langchain_docling/__init__.py
langchain_docling/_plugins.py
langchain_docling/loader.py
langchain_docling/picture_description.py
langchain_docling/py.typed
langchain_docling-2.0.0.dist-info/licenses/LICENSE
langchain_docling-2.0.0.dist-info/METADATA
langchain_docling-2.0.0.dist-info/WHEEL
langchain_docling-2.0.0.dist-info/entry_points.txt
langchain_docling-2.0.0.dist-info/top_level.txt
langchain_docling-2.0.0.dist-info/RECORD
