Metadata-Version: 2.4
Name: langchain-docling
Version: 2.0.0
Summary: Docling LangChain integration
Author-email: Panos Vagenas <pva@zurich.ibm.com>
Maintainer-email: Panos Vagenas <pva@zurich.ibm.com>, Michele Dolfi <dol@zurich.ibm.com>, Christoph Auer <cau@zurich.ibm.com>, Peter Staar <taa@zurich.ibm.com>
License-Expression: MIT
Project-URL: homepage, https://github.com/docling-project
Project-URL: repository, https://github.com/docling-project/docling-langchain
Project-URL: issues, https://github.com/docling-project/docling-langchain/issues
Project-URL: changelog, https://github.com/docling-project/docling-langchain/blob/main/CHANGELOG.md
Classifier: Operating System :: MacOS :: MacOS X
Classifier: Operating System :: POSIX :: Linux
Classifier: Operating System :: Microsoft :: Windows
Classifier: Development Status :: 5 - Production/Stable
Classifier: Intended Audience :: Developers
Classifier: Intended Audience :: Science/Research
Classifier: Topic :: Scientific/Engineering :: Artificial Intelligence
Classifier: Programming Language :: Python :: 3
Classifier: Programming Language :: Python :: 3.10
Classifier: Programming Language :: Python :: 3.11
Classifier: Programming Language :: Python :: 3.12
Classifier: Programming Language :: Python :: 3.13
Classifier: Programming Language :: Python :: 3.14
Requires-Python: <4,>=3.10
License-File: LICENSE
Requires-Dist: langchain-core~=1.0
Requires-Dist: docling~=2.26
Dynamic: license-file
